mpl_trajectory.py
mpl_trajectory-1.0.0.dist-info/LICENSE.txt
mpl_trajectory-1.0.0.dist-info/METADATA
mpl_trajectory-1.0.0.dist-info/WHEEL
mpl_trajectory-1.0.0.dist-info/top_level.txt
mpl_trajectory-1.0.0.dist-info/RECORD
