Metadata-Version: 2.1
Name: mpl-trajectory
Version: 1.0.0
Summary: A small package for matplotlib to show movement of trajectories in the form of animations.
Home-page: https://github.com/Hitthesurf/mpl_trajectory
Author: Mark Pearson
License: MIT
Platform: UNKNOWN
Classifier: Programming Language :: Python :: 3
Classifier: License :: OSI Approved :: MIT License
Classifier: Operating System :: OS Independent
Requires-Python: >=3.6
Requires-Dist: matplotlib
